{"chunk_definitions":[{"chunk_id":"csetup_chunk","chunk_label":"setup","document_id":"832C711","expansion_state":0,"options":{"engine":"r","include":false,"label":"setup"},"row":5,"row_count":1,"visible":true},{"chunk_id":"cqw2jdg8p1ams","chunk_label":"unnamed-chunk-1","document_id":"832C711","expansion_state":0,"options":{"engine":"r","label":"unnamed-chunk-1"},"row":33,"row_count":1,"visible":true},{"chunk_id":"c8u2dlpg9dc6q","chunk_label":"unnamed-chunk-2","document_id":"832C711","expansion_state":0,"options":{"engine":"r","label":"unnamed-chunk-11"},"row":43,"row_count":1,"visible":true},{"chunk_id":"cmdkqomctxxqh","chunk_label":"unnamed-chunk-3","document_id":"832C711","expansion_state":0,"options":{"engine":"r","label":"unnamed-chunk-12"},"row":54,"row_count":1,"visible":true},{"chunk_id":"czfm4tzuyu0tk","chunk_label":"unnamed-chunk-4","document_id":"832C711","expansion_state":0,"options":{"engine":"r","label":"unnamed-chunk-13"},"row":58,"row_count":1,"visible":true},{"chunk_id":"cm1tsvit9baqi","chunk_label":"unnamed-chunk-5","document_id":"832C711","expansion_state":0,"options":{"engine":"r","label":"unnamed-chunk-10"},"row":66,"row_count":1,"visible":true},{"chunk_id":"c6ms20hf6ixzz","chunk_label":"unnamed-chunk-6","document_id":"832C711","expansion_state":0,"options":{"engine":"r","label":"unnamed-chunk-9"},"row":72,"row_count":1,"visible":true},{"chunk_id":"c3a3awfegvalv","chunk_label":"unnamed-chunk-7","document_id":"832C711","expansion_state":0,"options":{"engine":"r","label":"unnamed-chunk-22"},"row":80,"row_count":1,"visible":true},{"chunk_id":"cyggi0cfk8w9j","chunk_label":"unnamed-chunk-8","document_id":"832C711","expansion_state":0,"options":{"engine":"r","label":"unnamed-chunk-23"},"row":85,"row_count":1,"visible":true}],"default_chunk_options":{"echo":true},"doc_write_time":1585123034,"working_dir":null}